{
  "$schema": "https://proj.org/schemas/v0.7/projjson.schema.json",
  "type": "ProjectedCRS",
  "name": "Polyconic",
  "base_crs": {
    "name": "Based upon the Everest 1830 ellipsoid",
    "datum": {
      "type": "GeodeticReferenceFrame",
      "name": "Based upon the Everest 1830 ellipsoid",
      "ellipsoid": {
        "name": "Everest 1830 (1975 Definition)",
        "semi_major_axis": 6377301.243,
        "inverse_flattening": 300.801700000002
      }
    },
    "coordinate_system": {
      "subtype": "ellipsoidal",
      "axis": [
        {
          "name": "Longitude",
          "abbreviation": "lon",
          "direction": "east",
          "unit": {
            "type": "AngularUnit",
            "name": "Degree",
            "conversion_factor": 0.0174532925199433
          }
        },
        {
          "name": "Latitude",
          "abbreviation": "lat",
          "direction": "north",
          "unit": {
            "type": "AngularUnit",
            "name": "Degree",
            "conversion_factor": 0.0174532925199433
          }
        }
      ]
    }
  },
  "conversion": {
    "name": "unnamed",
    "method": {
      "name": "American Polyconic",
      "id": {
        "authority": "EPSG",
        "code": 9818
      }
    },
    "parameters": [
      {
        "name": "False easting",
        "value": 0,
        "unit": {
          "type": "LinearUnit",
          "name": "Degree",
          "conversion_factor": 1
        },
        "id": {
          "authority": "EPSG",
          "code": 8806
        }
      },
      {
        "name": "False northing",
        "value": 0,
        "unit": {
          "type": "LinearUnit",
          "name": "Degree",
          "conversion_factor": 1
        },
        "id": {
          "authority": "EPSG",
          "code": 8807
        }
      },
      {
        "name": "Longitude of natural origin",
        "value": 84,
        "unit": {
          "type": "AngularUnit",
          "name": "Degree",
          "conversion_factor": 0.0174532925199433
        },
        "id": {
          "authority": "EPSG",
          "code": 8802
        }
      },
      {
        "name": "Latitude of natural origin",
        "value": 22,
        "unit": {
          "type": "AngularUnit",
          "name": "Degree",
          "conversion_factor": 0.0174532925199433
        },
        "id": {
          "authority": "EPSG",
          "code": 8801
        }
      }
    ]
  },
  "coordinate_system": {
    "subtype": "Cartesian",
    "axis": [
      {
        "name": "Easting",
        "abbreviation": "",
        "direction": "east",
        "unit": {
          "type": "LinearUnit",
          "name": "Degree",
          "conversion_factor": 1
        }
      },
      {
        "name": "Northing",
        "abbreviation": "",
        "direction": "north",
        "unit": {
          "type": "LinearUnit",
          "name": "Degree",
          "conversion_factor": 1
        }
      }
    ]
  },
  "id": {
    "authority": "EPSG",
    "code": 999000
  }
}