{
  "$schema": "https://proj.org/schemas/v0.7/projjson.schema.json",
  "type": "ProjectedCRS",
  "name": "PCS_CALI_BOG",
  "base_crs": {
    "name": "CGS_CartCali",
    "datum": {
      "type": "GeodeticReferenceFrame",
      "name": "San_Antonio",
      "ellipsoid": {
        "name": "International 1924 + Plano de Proyeccion 1000 msnm",
        "semi_major_axis": 6379388,
        "inverse_flattening": 297
      }
    },
    "coordinate_system": {
      "subtype": "ellipsoidal",
      "axis": [
        {
          "name": "Longitude",
          "abbreviation": "lon",
          "direction": "east",
          "unit": {
            "type": "AngularUnit",
            "name": "Degree",
            "conversion_factor": 0.0174532925199433
          }
        },
        {
          "name": "Latitude",
          "abbreviation": "lat",
          "direction": "north",
          "unit": {
            "type": "AngularUnit",
            "name": "Degree",
            "conversion_factor": 0.0174532925199433
          }
        }
      ]
    }
  },
  "conversion": {
    "name": "unnamed",
    "method": {
      "name": "Transverse Mercator",
      "id": {
        "authority": "EPSG",
        "code": 9807
      }
    },
    "parameters": [
      {
        "name": "Latitude of natural origin",
        "value": 3.44959194444444,
        "unit": {
          "type": "AngularUnit",
          "name": "Degree",
          "conversion_factor": 0.0174532925199433
        },
        "id": {
          "authority": "EPSG",
          "code": 8801
        }
      },
      {
        "name": "Longitude of natural origin",
        "value": -76.5470522222222,
        "unit": {
          "type": "AngularUnit",
          "name": "Degree",
          "conversion_factor": 0.0174532925199433
        },
        "id": {
          "authority": "EPSG",
          "code": 8802
        }
      },
      {
        "name": "Scale factor at natural origin",
        "value": 1,
        "unit": "unity",
        "id": {
          "authority": "EPSG",
          "code": 8805
        }
      },
      {
        "name": "False easting",
        "value": 110000,
        "unit": {
          "type": "LinearUnit",
          "name": "Meter",
          "conversion_factor": 1
        },
        "id": {
          "authority": "EPSG",
          "code": 8806
        }
      },
      {
        "name": "False northing",
        "value": 110000,
        "unit": {
          "type": "LinearUnit",
          "name": "Meter",
          "conversion_factor": 1
        },
        "id": {
          "authority": "EPSG",
          "code": 8807
        }
      }
    ]
  },
  "coordinate_system": {
    "subtype": "Cartesian",
    "axis": [
      {
        "name": "Easting",
        "abbreviation": "E",
        "direction": "east",
        "unit": {
          "type": "LinearUnit",
          "name": "Meter",
          "conversion_factor": 1
        }
      },
      {
        "name": "Northing",
        "abbreviation": "N",
        "direction": "north",
        "unit": {
          "type": "LinearUnit",
          "name": "Meter",
          "conversion_factor": 1
        }
      }
    ]
  }
}